vane/__init__.py
vane/__main__.py
vane/__version__.py
vane/activecomponentfinder.py
vane/core.py
vane/database.py
vane/filefetcher.py
vane/hash.py
vane/mimetype.py
vane/outputmanager.py
vane/passivepluginsfinder.py
vane/passivethemesfinder.py
vane/rejectunexpectedresponse.py
vane/retryonerrors.py
vane/setexpectedmimetype.py
vane/utils.py
vane/versionidentification.py
vane/vulnerabilitylister.py
vane2-2.4.1.dist-info/LICENSE.md
vane2-2.4.1.dist-info/METADATA
vane2-2.4.1.dist-info/WHEEL
vane2-2.4.1.dist-info/entry_points.txt
vane2-2.4.1.dist-info/top_level.txt
vane2-2.4.1.dist-info/RECORD
